HISTORY.rst
MANIFEST.in
README.rst
setup.py
kantonzugpdf/.DS_Store
kantonzugpdf/__init__.py
kantonzugpdf/report.py
kantonzugpdf.egg-info/PKG-INFO
kantonzugpdf.egg-info/SOURCES.txt
kantonzugpdf.egg-info/dependency_links.txt
kantonzugpdf.egg-info/namespace_packages.txt
kantonzugpdf.egg-info/not-zip-safe
kantonzugpdf.egg-info/requires.txt
kantonzugpdf.egg-info/top_level.txt
kantonzugpdf/fonts/FreeSans.ttf
kantonzugpdf/fonts/FreeSansBold.ttf
kantonzugpdf/fonts/FreeSansBoldOblique.ttf
kantonzugpdf/fonts/FreeSansOblique.ttf
kantonzugpdf/fonts/LICENSE
kantonzugpdf/resources/.DS_Store
kantonzugpdf/resources/logo_zug.png
kantonzugpdf/resources/logo_zug.svg
kantonzugpdf/tests/conftest.py
kantonzugpdf/tests/test_report.py