Metadata-Version: 1.1
Name: kantonzugpdf
Version: 0.3.1
Summary: A library to create PDF reports for the Canton of Zug
Home-page: http://github.com/seantis/kantonzugpdf
Author: Seantis GmbH
Author-email: info@seantis.ch
License: GPLv2
Platform: any
Classifier: Intended Audience :: Developers
Classifier: Programming Language :: Python
Classifier: Programming Language :: Python :: 3
Classifier: Topic :: Software Development :: Libraries :: Python Modules
Classifier: License :: OSI Approved :: GNU General Public License v2 (GPLv2)
